xander_cli/__init__.py
xander_cli/cli.py
xander_cli/xander.py
xander_cli/AIUnified/Chatbot.py
xander_cli/AIUnified/ChatbotPDF.py
xander_cli/AIUnified/ClassificationDL.py
xander_cli/AIUnified/ClassificationML.py
xander_cli/AIUnified/Forecaster.py
xander_cli/AIUnified/ImageModelTrainer.py
xander_cli/AIUnified/ImageTrainer.py
xander_cli/AIUnified/RegressionDL.py
xander_cli/AIUnified/RegressionML.py
xander_cli/AIUnified/RegressionUnified.py
xander_cli/AIUnified/TextModel.py
xander_cli/AIUnified/TextUnified.py
xander_cli/AIUnified/__init__.py
xander_cli/AIUnified/chatbot_interference.py
xander_cli-0.1.dist-info/METADATA
xander_cli-0.1.dist-info/WHEEL
xander_cli-0.1.dist-info/entry_points.txt
xander_cli-0.1.dist-info/top_level.txt
xander_cli-0.1.dist-info/RECORD
