Metadata-Version: 2.1
Name: xander-cli
Version: 0.1
Summary: Xander AI CLI for training AI models
Author: Atulit Gaur
Author-email: atulit23@xanderco.in
Classifier: Programming Language :: Python :: 3
Classifier: License :: OSI Approved :: MIT License
Classifier: Operating System :: OS Independent
Requires-Python: >=3.7
Requires-Dist: pandas
Requires-Dist: scikit-learn
Requires-Dist: tensorflow
Requires-Dist: keras
Requires-Dist: keras-tuner
Requires-Dist: joblib
Requires-Dist: requests
Requires-Dist: nltk
Requires-Dist: channels
Requires-Dist: asgiref
Requires-Dist: chardet
